<?xml version="1.0" encoding="utf-8"?>
<DocEntity xmlns:xsi="http://www.w3.org/2001/XMLSchema-instance" id="IfcPipeSegmentType" Name="IfcPipeSegmentType" UniqueId="6ff8bb62-5b12-4204-85f9-d8aea8bb8b00" DiagramNumber="0" BaseDefinition="IfcFlowSegmentType" EntityFlags="101">
	<Localization>
		<DocLocalization Name="Rohr - Typ" Locale="de" />
		<DocLocalization Name="Pipe Segment Type" Locale="en" />
		<DocLocalization Name="Type de tronçon de tuyauterie" Locale="fr" />
	</Localization>
	<Attributes>
		<DocAttribute Name="PredefinedType" UniqueId="7cf082e3-2380-49ba-be0e-eae30275e85d" DefinedType="IfcPipeSegmentTypeEnum" AttributeFlags="0" AggregationType="0" AggregationFlag="0">
			<Documentation>The type of pipe segment.</Documentation>
		</DocAttribute>
	</Attributes>
	<WhereRules>
		<DocWhereRule Name="CorrectPredefinedType" UniqueId="1061dd44-ebf9-4bf3-a4cb-f25073bdc29f">
			<Expression>(PredefinedType &lt;&gt; IfcPipeSegmentTypeEnum.USERDEFINED) OR
((PredefinedType = IfcPipeSegmentTypeEnum.USERDEFINED) AND EXISTS(SELF\IfcElementType.ElementType))</Expression>
		</DocWhereRule>
	</WhereRules>
</DocEntity>

